nonebot_plugin_mhguesser-0.2.7.dist-info/METADATA
nonebot_plugin_mhguesser-0.2.7.dist-info/WHEEL
nonebot_plugin_mhguesser-0.2.7.dist-info/entry_points.txt
nonebot_plugin_mhguesser-0.2.7.dist-info/licenses/LICENSE
nonebot_plugin_mhguesser/__init__.py
nonebot_plugin_mhguesser/config.py
nonebot_plugin_mhguesser/game.py
nonebot_plugin_mhguesser/render.py
nonebot_plugin_mhguesser/resources/data/monsters.json
nonebot_plugin_mhguesser/resources/templates/correct.html
nonebot_plugin_mhguesser/resources/templates/guess.html
nonebot_plugin_mhguesser-0.2.7.dist-info/RECORD
